torchgen/__init__.py
torchgen/version.py
torchgen/flow/__init__.py
torchgen/gan/__init__.py
torchgen/vae/__init__.py
torchgen-0.0.1.dist-info/LICENSE
torchgen-0.0.1.dist-info/METADATA
torchgen-0.0.1.dist-info/WHEEL
torchgen-0.0.1.dist-info/top_level.txt
torchgen-0.0.1.dist-info/RECORD
