Metadata-Version: 2.1
Name: torchgen
Version: 0.0.1
Summary: Ready to use implementations of state-of-the-art generative models in PyTorch
Home-page: https://github.com/mbarbetti/torchgen
Author: Matteo Barbetti
Author-email: matteo.barbetti@fi.infn.it
Maintainer: Matteo Barbetti
Maintainer-email: matteo.barbetti@fi.infn.it
License: MIT
Keywords: machine-learning,deep-learning,pytorch,generative-models,gan
Platform: UNKNOWN
Classifier: Development Status :: 3 - Alpha
Classifier: Intended Audience :: Education
Classifier: Intended Audience :: Developers
Classifier: Intended Audience :: Science/Research
Classifier: License :: OSI Approved :: MIT License
Classifier: Programming Language :: Python :: 3
Classifier: Programming Language :: Python :: 3 :: Only
Classifier: Programming Language :: Python :: 3.7
Classifier: Programming Language :: Python :: 3.8
Classifier: Programming Language :: Python :: 3.9
Classifier: Topic :: Scientific/Engineering
Classifier: Topic :: Scientific/Engineering :: Mathematics
Classifier: Topic :: Scientific/Engineering :: Artificial Intelligence
Classifier: Topic :: Software Development
Classifier: Topic :: Software Development :: Libraries
Classifier: Topic :: Software Development :: Libraries :: Python Modules
Requires-Python: >=3.7, <4
License-File: LICENSE
